milespy/__init__.py
milespy/configuration.py
milespy/filter.py
milespy/ls_indices.py
milespy/magnitudes.py
milespy/misc.py
milespy/repository.py
milespy/sfh.py
milespy/spectra.py
milespy/ssp_library.py
milespy/stellar_library.py
milespy/config_files/CALIFA-V1200.lsf
milespy/config_files/CALIFA-V500.lsf
milespy/config_files/EMILES.lsf
milespy/config_files/MUSE-WFM.lsf
milespy/config_files/ls_indices_full.def
milespy/config_files/sun_mod_001.fits
milespy/config_files/sun_reference_stis_002.fits
milespy/config_files/vega.sed
milespy/config_files/vega_from_koo.sed
milespy/config_files/filters/2MASS_2MASS.H.dat
milespy/config_files/filters/2MASS_2MASS.J.dat
milespy/config_files/filters/2MASS_2MASS.Ks.dat
milespy/config_files/filters/CFHT_CFH12k.B.dat
milespy/config_files/filters/CFHT_CFH12k.I.dat
milespy/config_files/filters/CFHT_CFH12k.R.dat
milespy/config_files/filters/CFHT_CFH12k.V.dat
milespy/config_files/filters/GALEX_GALEX.FUV.dat
milespy/config_files/filters/GALEX_GALEX.NUV.dat
milespy/config_files/filters/Generic_Bessell.B.dat
milespy/config_files/filters/Generic_Bessell.I.dat
milespy/config_files/filters/Generic_Bessell.R.dat
milespy/config_files/filters/Generic_Bessell.U.dat
milespy/config_files/filters/Generic_Bessell.V.dat
milespy/config_files/filters/HST_ACS_HRC.F220W.dat
milespy/config_files/filters/HST_ACS_HRC.F250W.dat
milespy/config_files/filters/HST_ACS_HRC.F330W.dat
milespy/config_files/filters/HST_ACS_HRC.F344N.dat
milespy/config_files/filters/HST_ACS_HRC.F435W.dat
milespy/config_files/filters/HST_ACS_HRC.F475W.dat
milespy/config_files/filters/HST_ACS_HRC.F555W.dat
milespy/config_files/filters/HST_ACS_HRC.F606W.dat
milespy/config_files/filters/HST_ACS_HRC.F625W.dat
milespy/config_files/filters/HST_ACS_HRC.F775W.dat
milespy/config_files/filters/HST_ACS_HRC.F814W.dat
milespy/config_files/filters/HST_ACS_WFC.F435W.dat
milespy/config_files/filters/HST_ACS_WFC.F475W.dat
milespy/config_files/filters/HST_ACS_WFC.F555W.dat
milespy-1.0rc5.dist-info/METADATA
milespy-1.0rc5.dist-info/WHEEL
milespy-1.0rc5.dist-info/licenses/LICENSE
milespy-1.0rc5.dist-info/RECORD
