Metadata-Version: 2.4
Name: milespy
Version: 1.0rc5
Summary: Wrapper for the MILES spectral library
Author-email: Isaac Alonso Asensio <isaac.alonso.asensio@iac.es>
Maintainer-email: Isaac Alonso Asensio <isaac.alonso.asensio@iac.es>
License-File: LICENSE
Requires-Python: >=3.10
Requires-Dist: astropy>=6
Requires-Dist: h5py<4,>=3.11.0
Requires-Dist: matplotlib~=3.7
Requires-Dist: numpy>=1.24
Requires-Dist: rcfile<0.2,>=0.1.4
Requires-Dist: requests<3,>=2.31.0
Requires-Dist: scipy>=1.10
Requires-Dist: spectres<3,>=2.2.2
Requires-Dist: specutils>=2.0
Requires-Dist: tqdm<5,>=4.66.4
